reqlcli/__init__.py
reql_cli-0.3.1.data/scripts/rql
reql_cli-0.3.1.dist-info/METADATA
reql_cli-0.3.1.dist-info/WHEEL
reql_cli-0.3.1.dist-info/RECORD
reql_cli-0.3.1.dist-info/DESCRIPTION.rst
reql_cli-0.3.1.dist-info/top_level.txt
reql_cli-0.3.1.dist-info/metadata.json
