Metadata-Version: 2.0
Name: reql-cli
Version: 0.3.1
Summary: Run RethinkDB ReQL commands from the terminal
Home-page: https://github.com/deontologician/reql_cli
Author: Josh Kuhn
Author-email: deontologician@gmail.com
License: MIT
Keywords: rethinkdb,reql,rql,cli,commandline
Platform: UNKNOWN
Classifier: Development Status :: 3 - Alpha
Classifier: Intended Audience :: Developers
Classifier: License :: OSI Approved :: MIT License
Classifier: Programming Language :: Python :: 2.7
Requires-Dist: rethinkdb (>=1.13)
Requires-Dist: pygments (>=1.6)
